jsonablr/__init__.py
jsonablr/main.py
jsonablr-2.0.1.dist-info/LICENSE
jsonablr-2.0.1.dist-info/METADATA
jsonablr-2.0.1.dist-info/WHEEL
jsonablr-2.0.1.dist-info/RECORD
