Metadata-Version: 2.1
Name: jsonablr
Version: 2.0.1
Summary: Serialize Pydantic models and non-JSONable types into a JSONable variable.
Home-page: https://github.com/frizzy/jsonablr.git
Author: Bernard van Niekerk
Author-email: bernard.van.niekerk@icloud.com
Requires-Python: >=3.8,<4.0
Classifier: Programming Language :: Python :: 3
Classifier: Programming Language :: Python :: 3.8
Classifier: Programming Language :: Python :: 3.9
Classifier: Programming Language :: Python :: 3.10
Classifier: Programming Language :: Python :: 3.11
Requires-Dist: pydantic (>=2.0,<3.0)
Project-URL: Repository, https://github.com/frizzy/jsonablr.git
